Workbook

Sheet Summary
A1: NVIDIA Equity Research & Financial Analysis | FY2024–FY2025
A3: Executive Dashboard
A5: Key Metric | B5: FY2025 | D5: Growth Metric | E5: FY25 vs FY24
A6: Revenue ($mm) | B6: =Financials!C4 -> 130497 | D6: Operating Income Growth | E6: =Financials!D7 -> 1.4703688
A7: Revenue Growth | B7: =Financials!D4 -> 1.1420341 | D7: Net Income Growth | E7: =Financials!D8 -> 1.4489247
A8: Operating Margin | B8: =Financials!C13 -> 0.62417527 | D8: Data Center Growth | E8: ='Revenue Mix'!D4 -> 1.4236928
A9: Net Margin | B9: =Financials!C14 -> 0.55848027 | D9: Gaming Growth | E9: ='Revenue Mix'!D5 -> 0.086436298
A12: Key Takeaways
A13: • Revenue increased from $60.9B in FY2024 to $130.5B in FY2025, a 114% increase.
A14: • Net income increased from $29.8B to $72.9B, substantially outpacing revenue growth.
A15: • Data Center was the primary growth engine, rising from $47.5B to $115.2B.
A16: • GAAP gross margin expanded from 72.7% to 75.0%.
A17: • The analysis highlights exceptional AI-driven growth, while Data Center concentration remains an important risk to monitor.

Sheet Financials
A1: NVIDIA Historical Financial Analysis
A3: Metric ($mm except EPS) | B3: FY2024 | C3: FY2025 | D3: YoY Growth
A4: Revenue | B4: 60922 | C4: 130497 | D4: =C4/B4-1 -> 1.1420341
A5: Gross Profit | B5: 44301 | C5: 97858 | D5: =C5/B5-1 -> 1.2089343
A6: Operating Expenses | B6: 11329 | C6: 16405 | D6: =C6/B6-1 -> 0.44805367
A7: Operating Income | B7: 32972 | C7: 81453 | D7: =C7/B7-1 -> 1.4703688
A8: Net Income | B8: 29760 | C8: 72880 | D8: =C8/B8-1 -> 1.4489247
A9: Diluted EPS ($, split-adjusted) | B9: 1.19 | C9: 2.94 | D9: =C9/B9-1 -> 1.4705882
A11: Profitability | B11: FY2024 | C11: FY2025 | D11: Change
A12: Gross Margin | B12: =B5/B4 -> 0.72717573 | C12: =C5/C4 -> 0.74988697 | D12: =C12-B12 -> 0.022711238
A13: Operating Margin | B13: =B7/B4 -> 0.54121664 | C13: =C7/C4 -> 0.62417527 | D13: =C13-B13 -> 0.082958631
A14: Net Margin | B14: =B8/B4 -> 0.48849348 | C14: =C8/C4 -> 0.55848027 | D14: =C14-B14 -> 0.069986788
A15: Operating Expense % Revenue | B15: =B6/B4 -> 0.1859591 | C15: =C6/C4 -> 0.1257117 | D15: =C15-B15 -> -0.060247393
A18: Source Notes
A19: FY2024 | B19: NVIDIA FY2024 results | C19: https://investor.nvidia.com/news/press-release-details/2024/NVIDIA-Announces-Financial-Results-for-Fourth-Quarter-and-Fiscal-2024/
A20: FY2025 | B20: NVIDIA FY2025 results | C20: https://investor.nvidia.com/news/press-release-details/2025/NVIDIA-Announces-Financial-Results-for-Fourth-Quarter-and-Fiscal-2025/default.aspx

Sheet Revenue Mix
A1: NVIDIA Revenue by Market Platform
A3: Market Platform ($mm) | B3: FY2024 | C3: FY2025 | D3: YoY Growth | F3: Revenue Mix | G3: FY2024 | H3: FY2025
A4: Data Center | B4: 47525 | C4: 115186 | D4: =C4/B4-1 -> 1.4236928 | F4: Data Center % | G4: =B4/$B$9 -> 0.78009586 | H4: =C4/$C$9 -> 0.88267163
A5: Gaming | B5: 10447 | C5: 11350 | D5: =C5/B5-1 -> 0.086436298 | F5: Gaming % | G5: =B5/$B$9 -> 0.17148157 | H5: =C5/$C$9 -> 0.08697518
A6: Professional Visualization | B6: 1553 | C6: 1878 | D6: =C6/B6-1 -> 0.20927238 | F6: Pro Viz % | G6: =B6/$B$9 -> 0.025491612 | H6: =C6/$C$9 -> 0.014391135
A7: Automotive | B7: 1091 | C7: 1694 | D7: =C7/B7-1 -> 0.55270394 | F7: Automotive % | G7: =B7/$B$9 -> 0.017908145 | H7: =C7/$C$9 -> 0.012981141
A8: OEM and Other | B8: 306 | C8: 389 | D8: =C8/B8-1 -> 0.27124183 | F8: OEM & Other % | G8: =B8/$B$9 -> 0.0050228161 | H8: =C8/$C$9 -> 0.0029809114
A9: Total Revenue | B9: 60922 | C9: 130497 | D9: =C9/B9-1 -> 1.1420341

Sheet Investment Thesis
A1: Investment Thesis — NVIDIA FY2024–FY2025
A3: Bull Case
A4: • AI infrastructure demand drove extraordinary Data Center expansion in FY2025.
A5: • Revenue more than doubled while operating income and net income grew even faster.
A6: • High gross margins indicate substantial economic value in NVIDIA's accelerated-computing platform.
A8: Key Risks
A9: • A very large share of growth is tied to Data Center and AI infrastructure spending.
A10: • Competition, customer concentration, supply constraints, export restrictions, and rapid technology shifts can affect future growth.
A11: • Exceptional historical growth rates should not automatically be assumed to continue indefinitely.
A13: Analyst Conclusion
A14: • FY2025 represented a major step-up in NVIDIA's scale and profitability.
A15: • The strongest evidence is 114% revenue growth, 147% operating-income growth, and 145% net-income growth.
A16: • A next step would be adding valuation work such as DCF and comparable-company analysis.

Sheet Sources
A1: Source | B1: Use | C1: URL
A2: NVIDIA FY2025 Results | B2: FY2025/FY2024 GAAP summary and market-platform revenue | C2: https://investor.nvidia.com/news/press-release-details/2025/NVIDIA-Announces-Financial-Results-for-Fourth-Quarter-and-Fiscal-2025/default.aspx
A3: NVIDIA FY2024 Results | B3: Cross-check FY2024 GAAP results | C3: https://investor.nvidia.com/news/press-release-details/2024/NVIDIA-Announces-Financial-Results-for-Fourth-Quarter-and-Fiscal-2024/
A4: NVIDIA Annual Reports | B4: Official annual-report archive | C4: https://investor.nvidia.com/financial-info/annual-reports-and-proxies/default.aspx
